LICENSE
MANIFEST.in
README.rst
pavement.py
requirements-dev.txt
requirements.txt
setup.py
tox.ini
bts/__init__.py
bts/http_rpc.py
bts/main.py
bts/metadata.py
bts.egg-info/PKG-INFO
bts.egg-info/SOURCES.txt
bts.egg-info/dependency_links.txt
bts.egg-info/entry_points.txt
bts.egg-info/not-zip-safe
bts.egg-info/requires.txt
bts.egg-info/top_level.txt
bts/ws/__init__.py
bts/ws/base_protocol.py
bts/ws/statistics_protocol.py
bts/ws/trade_protocol.py
bts/ws/transfer_protocol.py
docs/Makefile
docs/make.bat
docs/source/README
docs/source/conf.py
docs/source/index.rst
docs/source/_static/.gitkeep
tests/test_main.py